pymonzo/__init__.py
pymonzo/client.py
pymonzo/exceptions.py
pymonzo/py.typed
pymonzo/resources.py
pymonzo/settings.py
pymonzo/utils.py
pymonzo/accounts/__init__.py
pymonzo/accounts/enums.py
pymonzo/accounts/resources.py
pymonzo/accounts/schemas.py
pymonzo/attachments/__init__.py
pymonzo/attachments/resources.py
pymonzo/attachments/schemas.py
pymonzo/balance/__init__.py
pymonzo/balance/resources.py
pymonzo/balance/schemas.py
pymonzo/feed/__init__.py
pymonzo/feed/resources.py
pymonzo/feed/schemas.py
pymonzo/pots/__init__.py
pymonzo/pots/resources.py
pymonzo/pots/schemas.py
pymonzo/transactions/__init__.py
pymonzo/transactions/enums.py
pymonzo/transactions/resources.py
pymonzo/transactions/schemas.py
pymonzo/webhooks/__init__.py
pymonzo/webhooks/resources.py
pymonzo/webhooks/schemas.py
pymonzo/whoami/__init__.py
pymonzo/whoami/resources.py
pymonzo/whoami/schemas.py
pymonzo-2.2.1.dist-info/LICENSE
pymonzo-2.2.1.dist-info/WHEEL
pymonzo-2.2.1.dist-info/METADATA
pymonzo-2.2.1.dist-info/RECORD
