Metadata-Version: 2.1
Name: pymonzo
Version: 2.2.1
Summary: Modern Python API client for Monzo public API.
Keywords: monzo,api
Author-email: Paweł Adamczak <pawel.ad@gmail.com>
Requires-Python: >=3.8
Classifier: Development Status :: 5 - Production/Stable
Classifier: Intended Audience :: Developers
Classifier: License :: OSI Approved :: Mozilla Public License 2.0 (MPL 2.0)
Classifier: Operating System :: OS Independent
Classifier: Programming Language :: Python
Classifier: Programming Language :: Python :: 3
Classifier: Programming Language :: Python :: 3.8
Classifier: Programming Language :: Python :: 3.9
Classifier: Programming Language :: Python :: 3.10
Classifier: Programming Language :: Python :: 3.11
Classifier: Programming Language :: Python :: 3.12
Classifier: Typing :: Typed
Requires-Dist: Authlib
Requires-Dist: httpx
Requires-Dist: pydantic-settings
Requires-Dist: pydantic>2
Requires-Dist: typing_extensions; python_version<'3.11'
Requires-Dist: pymonzo[tests,docs] ; extra == "dev"
Requires-Dist: black ; extra == "dev"
Requires-Dist: interrogate ; extra == "dev"
Requires-Dist: isort ; extra == "dev"
Requires-Dist: ruff ; extra == "dev"
Requires-Dist: mypy<1.11.0 ; extra == "dev"
Requires-Dist: rich ; extra == "dev"
Requires-Dist: flit ; extra == "dev"
Requires-Dist: nox ; extra == "dev"
Requires-Dist: mkdocs ; extra == "docs"
Requires-Dist: mkdocs-gen-files ; extra == "docs"
Requires-Dist: mkdocs-include-markdown-plugin ; extra == "docs"
Requires-Dist: mkdocs-literate-nav ; extra == "docs"
Requires-Dist: mkdocs-material ; extra == "docs"
Requires-Dist: mkdocs-section-index ; extra == "docs"
Requires-Dist: mkdocstrings[python] ; extra == "docs"
Requires-Dist: coverage[toml] ; extra == "tests"
Requires-Dist: freezegun ; extra == "tests"
Requires-Dist: polyfactory ; extra == "tests"
Requires-Dist: pytest ; extra == "tests"
Requires-Dist: pytest-mock ; extra == "tests"
Requires-Dist: pytest-recording ; extra == "tests"
Requires-Dist: python-dotenv ; extra == "tests"
Requires-Dist: respx ; extra == "tests"
Requires-Dist: vcrpy-encrypt ; extra == "tests"
Project-URL: Documentation, https://pymonzo.readthedocs.io/
Project-URL: GitHub, https://github.com/pawelad/pymonzo
Project-URL: Homepage, https://pymonzo.pawelad.dev/
Project-URL: Issues, https://github.com/pawelad/pymonzo/issues
Provides-Extra: dev
Provides-Extra: docs
Provides-Extra: tests
